{
  "passengers": [
    {
      "fullname": "Mikey Perara",
      "id": 1,
      "checkedIn": true,
      "baggage": "hold-only",
      "checkInDate": 1646955284707
    },
    {
      "id": 2,
      "fullname": "Theodore Highland-Perara",
      "checkedIn": false,
      "checkInDate": null,
      "baggage": "none"
    },
    {
      "id": 3,
      "fullname": "Frank Lunde",
      "checkedIn": false,
      "checkInDate": null,
      "baggage": "none"
    },
    {
      "id": 4,
      "fullname": "Edgar Lunde",
      "checkedIn": true,
      "checkInDate": null,
      "baggage": "none"
    },
    {
      "id": 5,
      "fullname": "Henry Lunde",
      "checkedIn": true,
      "checkInDate": null,
      "baggage": "none"
    }
  ]
}